data_prep/__init__.py
data_prep/conftest.py
data_prep/tdd_utility.py
py_data_framework-0.0.1.dist-info/LICENSE
py_data_framework-0.0.1.dist-info/METADATA
py_data_framework-0.0.1.dist-info/WHEEL
py_data_framework-0.0.1.dist-info/top_level.txt
py_data_framework-0.0.1.dist-info/RECORD
