Metadata-Version: 2.1
Name: py-data-framework
Version: 0.0.1
Summary: Data engineering & Data science Framework
Home-page: https://github.com/madedotcom/py-analytics
Author: Made.com
Author-email: analytics@made.com
License: UNKNOWN
Platform: UNKNOWN
Classifier: Programming Language :: Python :: 3
Classifier: License :: OSI Approved :: MIT License
Classifier: Operating System :: OS Independent
Requires-Python: >=3.6
